smali/__init__.py
smali/attributes.py
smali/block.py
smali/exceptions.py
smali/literals.py
smali/modifiers.py
smali/qualifiers.py
smali/smali_file.py
smali/statements.py
smali/tokens.py
smali/utils.py
smali-0.2.5.dist-info/LICENSE.txt
smali-0.2.5.dist-info/METADATA
smali-0.2.5.dist-info/WHEEL
smali-0.2.5.dist-info/top_level.txt
smali-0.2.5.dist-info/zip-safe
smali-0.2.5.dist-info/RECORD
