Metadata-Version: 2.1
Name: smali
Version: 0.2.5
Summary: A library for parsing and unparsing smali files for programatic modification
Home-page: https://github.com/UnknownCollections/pysmali
Author: Anonymous
License: Unlicense
Project-URL: Bug Tracker, https://github.com/UnknownCollections/pysmali/issues
Project-URL: Documentation, https://github.com/UnknownCollections/pysmali/wiki
Project-URL: Source, https://github.com/UnknownCollections/pysmali
Keywords: smali,parser,unparser,formatter,java,android,apk
Platform: UNKNOWN
Classifier: Development Status :: 4 - Beta
Classifier: Intended Audience :: Developers
Classifier: License :: OSI Approved :: The Unlicense (Unlicense)
Classifier: Operating System :: OS Independent
Classifier: Programming Language :: Python :: 3
Classifier: Programming Language :: Python :: 3 :: Only
Classifier: Programming Language :: Python :: 3.8
Classifier: Programming Language :: Python :: 3.9
Classifier: Programming Language :: Python :: 3.10
Classifier: Topic :: Software Development
Classifier: Topic :: Software Development :: Assemblers
Classifier: Topic :: Software Development :: Build Tools
Classifier: Topic :: Software Development :: Compilers
Classifier: Topic :: Software Development :: Disassemblers
Classifier: Topic :: Software Development :: Interpreters
Classifier: Topic :: Software Development :: Libraries
Classifier: Topic :: Software Development :: Libraries :: Java Libraries
Classifier: Topic :: Software Development :: Libraries :: Python Modules
Classifier: Topic :: Software Development :: Pre-processors
Requires-Python: >=3.8
